setup.py
src/fingerprint_reader/__init__.py
src/fingerprint_reader/fingerprint.py
waveshare_fingerprint_reader_adaptor_swkim-0.0.1.dist-info/METADATA
waveshare_fingerprint_reader_adaptor_swkim-0.0.1.dist-info/WHEEL
waveshare_fingerprint_reader_adaptor_swkim-0.0.1.dist-info/licenses/LICENSE
waveshare_fingerprint_reader_adaptor_swkim-0.0.1.dist-info/RECORD
